{"estimator": {"params": {"C": 1.0, "cache_size": 1000.0, "class_weight": "balanced", "coef0": 0.0, "decision_function_shape": "ovr", "degree": 3, "gamma": "auto", "kernel": "rbf", "max_iter": -1, "probability": false, "random_state": null, "shrinking": true, "tol": 0.001, "verbose": false}, "runtime": "0:01:18.752670", "classifier": "SVC(C=1.0, cache_size=1000.0, class_weight='balanced', coef0=0.0,\n  decision_function_shape='ovr', degree=3, gamma='auto', kernel='rbf',\n  max_iter=-1, probability=False, random_state=None, shrinking=True,\n  tol=0.001, verbose=False)"}, "accuracy_score": 0.9809506059610282, "balanced_accuracy": 0.9801558874258348, "confusion_matrix": [[185255, 3571], [313, 14752]], "f1_score": 0.8836707799209297, "precision_score": 0.8051083337881352, "recall_score": 0.9792233654165283, "roc_auc_score": 0.9801558874258348, "train_percent": 0.26, "reduced_by": 1}