{"estimator": {"params": {"C": 1.0, "cache_size": 1000.0, "class_weight": "balanced", "coef0": 0.0, "decision_function_shape": "ovr", "degree": 3, "gamma": "auto", "kernel": "rbf", "max_iter": -1, "probability": false, "random_state": null, "shrinking": true, "tol": 0.001, "verbose": false}, "runtime": "0:00:03.312140", "classifier": "SVC(C=1.0, cache_size=1000.0, class_weight='balanced', coef0=0.0,\n    decision_function_shape='ovr', degree=3, gamma='auto', kernel='rbf',\n    max_iter=-1, probability=False, random_state=None, shrinking=True,\n    tol=0.001, verbose=False)"}, "accuracy_score": 0.9674413005971162, "balanced_accuracy": 0.9630234911251734, "confusion_matrix": [[245823, 8072], [854, 19402]], "f1_score": 0.8129897339199665, "precision_score": 0.7061949479507899, "recall_score": 0.9578396524486572, "roc_auc_score": 0.9630234911251735, "train_percent": 0.005, "reduced_by": 1}