{"estimator": {"params": {"algorithm": "auto", "leaf_size": 30, "metric": "minkowski", "metric_params": null, "n_jobs": -1, "n_neighbors": 1, "p": 1, "weights": "uniform"}, "runtime": "0:00:29.604476", "classifier": "KNeighborsClassifier(algorithm='auto', leaf_size=30, metric='minkowski',\n           metric_params=None, n_jobs=-1, n_neighbors=1, p=1,\n           weights='uniform')"}, "accuracy_score": 0.9995607392692537, "balanced_accuracy": 0.9974488078323507, "confusion_matrix": [[149117, 51], [16, 3345]], "f1_score": 0.9900843569631493, "precision_score": 0.984982332155477, "recall_score": 0.9952395120499852, "roc_auc_score": 0.9974488078323508, "train_percent": 0.11, "reduced_by": 3}