{"estimator": {"params": {"algorithm": "auto", "leaf_size": 30, "metric": "minkowski", "metric_params": null, "n_jobs": -1, "n_neighbors": 3, "p": 1, "weights": "uniform"}, "runtime": "0:00:37.774327", "classifier": "KNeighborsClassifier(algorithm='auto', leaf_size=30, metric='minkowski',\n           metric_params=None, n_jobs=-1, n_neighbors=3, p=1,\n           weights='uniform')"}, "accuracy_score": 0.9990285357531136, "balanced_accuracy": 0.9970360669701106, "confusion_matrix": [[347022, 233], [128, 24221]], "f1_score": 0.9926029137553019, "precision_score": 0.9904719064365748, "recall_score": 0.9947431106000246, "roc_auc_score": 0.9970360669701106, "train_percent": 0.35, "reduced_by": 3}