{"estimator": {"params": {"algorithm": "auto", "leaf_size": 30, "metric": "minkowski", "metric_params": null, "n_jobs": -1, "n_neighbors": 1, "p": 1, "weights": "uniform"}, "runtime": "0:00:50.572389", "classifier": "KNeighborsClassifier(algorithm='auto', leaf_size=30, metric='minkowski',\n           metric_params=None, n_jobs=-1, n_neighbors=1, p=1,\n           weights='uniform')"}, "accuracy_score": 0.9804039704442897, "balanced_accuracy": 0.9257132807318518, "confusion_matrix": [[522895, 6002], [5089, 31996]], "f1_score": 0.8522834729565947, "precision_score": 0.8420443181220064, "recall_score": 0.8627747067547525, "roc_auc_score": 0.9257132807318517, "train_percent": 0.01, "reduced_by": 3}