{"estimator": {"params": {"algorithm": "auto", "leaf_size": 30, "metric": "minkowski", "metric_params": null, "n_jobs": -1, "n_neighbors": 1, "p": 1, "weights": "uniform"}, "runtime": "0:00:19.169759", "classifier": "KNeighborsClassifier(algorithm='auto', leaf_size=30, metric='minkowski',\n           metric_params=None, n_jobs=-1, n_neighbors=1, p=1,\n           weights='uniform')"}, "accuracy_score": 0.9999705677743886, "balanced_accuracy": 0.999381725755824, "confusion_matrix": [[368829, 5], [6, 4900]], "f1_score": 0.9988788094995412, "precision_score": 0.9989806320081549, "recall_score": 0.9987770077456176, "roc_auc_score": 0.999381725755824, "train_percent": 0.06, "reduced_by": 1}