{"estimator": {"params": {"algorithm": "auto", "leaf_size": 30, "metric": "minkowski", "metric_params": null, "n_jobs": -1, "n_neighbors": 1, "p": 1, "weights": "uniform"}, "runtime": "0:00:47.103843", "classifier": "KNeighborsClassifier(algorithm='auto', leaf_size=30, metric='minkowski',\n           metric_params=None, n_jobs=-1, n_neighbors=1, p=1,\n           weights='uniform')"}, "accuracy_score": 0.9984700771661809, "balanced_accuracy": 0.9951059458602663, "confusion_matrix": [[165704, 157], [117, 13116]], "f1_score": 0.9896627178751981, "precision_score": 0.9881714759285768, "recall_score": 0.9911584674676944, "roc_auc_score": 0.9951059458602663, "train_percent": 0.35, "reduced_by": 4}