{"estimator": {"params": {"C": 1.0, "class_weight": "balanced", "dual": false, "fit_intercept": true, "intercept_scaling": 1, "loss": "squared_hinge", "max_iter": 100.0, "multi_class": "ovr", "penalty": "l2", "random_state": null, "tol": 1e-05, "verbose": 0}, "runtime": "0:00:01.308677", "classifier": "LinearSVC(C=1.0, class_weight='balanced', dual=False, fit_intercept=True,\n     intercept_scaling=1, loss='squared_hinge', max_iter=100.0,\n     multi_class='ovr', penalty='l2', random_state=None, tol=1e-05,\n     verbose=0)"}, "accuracy_score": 0.973412535989281, "balanced_accuracy": 0.9823236896280674, "confusion_matrix": [[259658, 7461], [139, 18591]], "f1_score": 0.8302889553838595, "precision_score": 0.7136112390603409, "recall_score": 0.9925787506673786, "roc_auc_score": 0.9823236896280673, "train_percent": 0.5, "reduced_by": 1}