{"estimator": {"params": {"class_weight": null, "criterion": "gini", "max_depth": 15, "max_features": 10, "max_leaf_nodes": null, "min_impurity_decrease": 0.0, "min_impurity_split": null, "min_samples_leaf": 1, "min_samples_split": 2, "min_weight_fraction_leaf": 0.0, "presort": false, "random_state": null, "splitter": "best"}, "runtime": "0:00:00.150748", "classifier": "DecisionTreeClassifier(class_weight=None, criterion='gini', max_depth=15,\n            max_features=10, max_leaf_nodes=None,\n            min_impurity_decrease=0.0, min_impurity_split=None,\n            min_samples_leaf=1, min_samples_split=2,\n            min_weight_fraction_leaf=0.0, presort=False, random_state=None,\n            splitter='best')"}, "accuracy_score": 0.999614890885751, "balanced_accuracy": 0.9943669619854548, "confusion_matrix": [[83790, 12], [21, 1867]], "f1_score": 0.9912397132997081, "precision_score": 0.9936136242682277, "recall_score": 0.9888771186440678, "roc_auc_score": 0.9943669619854549, "train_percent": 0.5, "reduced_by": 0}