{"estimator": {"params": {"class_weight": null, "criterion": "gini", "max_depth": 20, "max_features": 11, "max_leaf_nodes": null, "min_impurity_decrease": 0.0, "min_impurity_split": null, "min_samples_leaf": 1, "min_samples_split": 2, "min_weight_fraction_leaf": 0.0, "presort": false, "random_state": null, "splitter": "best"}, "runtime": "0:00:00.373526", "classifier": "DecisionTreeClassifier(class_weight=None, criterion='gini', max_depth=20,\n            max_features=11, max_leaf_nodes=None,\n            min_impurity_decrease=0.0, min_impurity_split=None,\n            min_samples_leaf=1, min_samples_split=2,\n            min_weight_fraction_leaf=0.0, presort=False, random_state=None,\n            splitter='best')"}, "accuracy_score": 0.9988280537446057, "balanced_accuracy": 0.997085647826772, "confusion_matrix": [[373627, 340], [129, 26093]], "f1_score": 0.9910929636311842, "precision_score": 0.987137290508077, "recall_score": 0.9950804667836168, "roc_auc_score": 0.997085647826772, "train_percent": 0.3, "reduced_by": 4}