{"estimator": {"params": {"class_weight": null, "criterion": "gini", "max_depth": 30, "max_features": 13, "max_leaf_nodes": null, "min_impurity_decrease": 0.0, "min_impurity_split": null, "min_samples_leaf": 1, "min_samples_split": 2, "min_weight_fraction_leaf": 0.0, "presort": false, "random_state": null, "splitter": "best"}, "runtime": "0:00:00.579956", "classifier": "DecisionTreeClassifier(class_weight=None, criterion='gini', max_depth=30,\n            max_features=13, max_leaf_nodes=None,\n            min_impurity_decrease=0.0, min_impurity_split=None,\n            min_samples_leaf=1, min_samples_split=2,\n            min_weight_fraction_leaf=0.0, presort=False, random_state=None,\n            splitter='best')"}, "accuracy_score": 0.9992964588428424, "balanced_accuracy": 0.9967690439934865, "confusion_matrix": [[165817, 44], [82, 13151]], "f1_score": 0.9952323293476616, "precision_score": 0.9966654035619553, "recall_score": 0.9938033703619739, "roc_auc_score": 0.9967690439934865, "train_percent": 0.35, "reduced_by": 2}